pylrctool/__init__.py
pylrctool/exceptions.py
pylrctool/lrcevent.py
pylrctool/lrcfile.py
pylrctool/regex.py
pylrctool-0.2.0.dist-info/licenses/LICENSE
pylrctool-0.2.0.dist-info/METADATA
pylrctool-0.2.0.dist-info/WHEEL
pylrctool-0.2.0.dist-info/top_level.txt
pylrctool-0.2.0.dist-info/RECORD
