Metadata-Version: 2.4
Name: pylrctool
Version: 0.2.0
Summary: Library to create and modify lrc files.
Author: varyg
Project-URL: homepage, https://github.com/varyg1001/pylrctool
Requires-Python: <3.14,>=3.10
License-File: LICENSE
Requires-Dist: pendulum>=3.1.0
Requires-Dist: sortedcontainers>=2.4.0
Requires-Dist: srt>=3.5.3
Dynamic: license-file
